{
	"sn": "facebook",
	"id": "100090020620374",
	"name": "",
	"amountFriends": "",
	"screenname": "Denise Morais",
	"birthdate": "",
	"country": "",
	"isAvatarExists": false,
	"cookie": [
		{
			"domain": ".facebook.com",
			"expirationDate": 1709943192.551305,
			"hostOnly": false,
			"httpOnly": true,
			"name": "sb",
			"path": "/",
			"sameSite": "no_restriction",
			"secure": true,
			"session": false,
			"storeId": "0",
			"value": "FF_cYzOSiXDrDC1DLnOlfoTZ"
		},
		{
			"domain": ".facebook.com",
			"expirationDate": 1709943091.943217,
			"hostOnly": false,
			"httpOnly": true,
			"name": "datr",
			"path": "/",
			"sameSite": "no_restriction",
			"secure": true,
			"session": false,
			"storeId": "0",
			"value": "FF_cYymVAbunIq3hTM9zJzh9"
		},
		{
			"domain": ".facebook.com",
			"expirationDate": 1675987992.551241,
			"hostOnly": false,
			"httpOnly": false,
			"name": "locale",
			"path": "/",
			"sameSite": "no_restriction",
			"secure": true,
			"session": false,
			"storeId": "0",
			"value": "pt_BR"
		},
		{
			"domain": ".facebook.com",
			"expirationDate": 1706982889.541725,
			"hostOnly": false,
			"httpOnly": false,
			"name": "c_user",
			"path": "/",
			"sameSite": "no_restriction",
			"secure": true,
			"session": false,
			"storeId": "0",
			"value": "100090030159306"
		},
		{
			"domain": ".facebook.com",
			"expirationDate": 1706967809.296672,
			"hostOnly": false,
			"httpOnly": false,
			"name": "i_user",
			"path": "/",
			"sameSite": "no_restriction",
			"secure": true,
			"session": false,
			"storeId": "0",
			"value": "100090020620374"
		},
		{
			"domain": ".facebook.com",
			"hostOnly": false,
			"httpOnly": false,
			"name": "usida",
			"path": "/",
			"sameSite": "no_restriction",
			"secure": true,
			"session": true,
			"storeId": "0",
			"value": "eyJ2ZXIiOjEsImlkIjoiQXJwaWJ3ZWhuOG5sYiIsInRpbWUiOjE2NzU0MzIzODJ9"
		},
		{
			"domain": ".facebook.com",
			"expirationDate": 1676051960,
			"hostOnly": false,
			"httpOnly": false,
			"name": "wd",
			"path": "/",
			"sameSite": "lax",
			"secure": true,
			"session": false,
			"storeId": "0",
			"value": "1920x937"
		},
		{
			"domain": ".facebook.com",
			"expirationDate": 1706982889.541849,
			"hostOnly": false,
			"httpOnly": true,
			"name": "xs",
			"path": "/",
			"sameSite": "no_restriction",
			"secure": true,
			"session": false,
			"storeId": "0",
			"value": "39%3Aqtv34kzynTBd7Q%3A2%3A1675386743%3A-1%3A-1%3A%3AAcXiuQo1MGL39hMinqq6JcL0iSdcnkP4yl0hZb_abQ"
		},
		{
			"domain": ".facebook.com",
			"expirationDate": 1683222899.788801,
			"hostOnly": false,
			"httpOnly": true,
			"name": "fr",
			"path": "/",
			"sameSite": "no_restriction",
			"secure": true,
			"session": false,
			"storeId": "0",
			"value": "0OBMQzWsI4RRXVjln.AWX5rui_Sn_d8qmeNh9Q60yuZZY.Bj3VhO.L8.AAA.0.0.Bj3VhY.AWVq71kp5F4"
		}
	],
	"lastEventDate": "03.02.2023 18:05 5 - Atividade Dias 6 a 8",
	"status": 2
}